brainmaze_zmq/__init__.py
brainmaze_zmq/abstract.py
brainmaze_zmq/utils.py
tests/__init__.py
tests/conftest.py
tests/constants.py
tests/test_dummy.py
brainmaze_zmq-0.0.1.dist-info/LICENSE
brainmaze_zmq-0.0.1.dist-info/METADATA
brainmaze_zmq-0.0.1.dist-info/WHEEL
brainmaze_zmq-0.0.1.dist-info/top_level.txt
brainmaze_zmq-0.0.1.dist-info/RECORD
